s3dxrd/__init__.py
s3dxrd/measurement/Id11.py
s3dxrd/measurement/__init__.py
s3dxrd/measurement/raw_measurements.py
s3dxrd/regression/__init__.py
s3dxrd/regression/bayesian.py
s3dxrd/regression/wlsq.py
s3dxrd/utils/__init__.py
s3dxrd/utils/analytical_strain_fields.py
s3dxrd/utils/compliance.py
s3dxrd/utils/forward_model.py
s3dxrd/utils/grain_fitter.py
s3dxrd/utils/measurement_converter.py
s3dxrd/utils/mesher.py
s3dxrd/utils/peak_mapper.py
s3dxrd/utils/random_measurements.py
s3dxrd/utils/reconstruct_grainshapes.py
s3dxrd/utils/save.py
s3dxrd/utils/scanning_transform.py
s3dxrd/utils/slice_matcher.py
s3dxrd/utils/topology.py
s3dxrd-0.0.10.dist-info/LICENSE
s3dxrd-0.0.10.dist-info/METADATA
s3dxrd-0.0.10.dist-info/WHEEL
s3dxrd-0.0.10.dist-info/top_level.txt
s3dxrd-0.0.10.dist-info/RECORD
