Metadata-Version: 2.1
Name: s3dxrd
Version: 0.0.10
Summary: Tools for intragranular strain estimation with s3dxrd data.
Home-page: https://github.com/AxelHenningsson/scanning-xray-diffraction
Author: Axel Henningsson
Author-email: nilsaxelhenningsson@gmail.com
License: UNKNOWN
Project-URL: Documentation, https://axelhenningsson.github.io/scanning-xray-diffraction/
Platform: UNKNOWN
Classifier: Programming Language :: Python :: 3
Classifier: License :: OSI Approved :: MIT License
Classifier: Operating System :: OS Independent
Requires-Python: >=3.6
License-File: LICENSE
Requires-Dist: numpy (>=1.20.0)
Requires-Dist: scipy
Requires-Dist: scikit-image (>=0.17.2)
Requires-Dist: torch (>=1.6.0)
Requires-Dist: h5py
Requires-Dist: matplotlib
Requires-Dist: numba (>=0.53.1)
Requires-Dist: Shapely (>=1.7.0)
Requires-Dist: pyevtk (>=1.1.2)
Requires-Dist: xfab (>=0.0.4)
Requires-Dist: fabio (>=0.10.2)
Requires-Dist: ImageD11 (>=1.9.7)
